freshpy/__init__.py
freshpy/api.py
freshpy/core.py
freshpy/tickets.py
freshpy/errors/__init__.py
freshpy/errors/exceptions.py
freshpy/errors/handlers.py
freshpy/utils/__init__.py
freshpy/utils/core_utils.py
freshpy/utils/log_utils.py
freshpy/utils/version.py
freshpy-1.1.0.dist-info/LICENSE
freshpy-1.1.0.dist-info/METADATA
freshpy-1.1.0.dist-info/WHEEL
freshpy-1.1.0.dist-info/top_level.txt
freshpy-1.1.0.dist-info/RECORD
