Metadata-Version: 2.1
Name: freshpy
Version: 1.1.0
Summary: A Python toolset for utilizing the Freshservice API
Home-page: https://github.com/jeffshurtliff/freshpy
Author: Jeff Shurtliff
Author-email: jeff.shurtliff@rsa.com
License: UNKNOWN
Project-URL: Change Log, https://freshpy.readthedocs.io/en/latest/changelog.html
Project-URL: Issue Tracker, https://github.com/jeffshurtliff/freshpy/issues
Platform: UNKNOWN
Classifier: Development Status :: 4 - Beta
Classifier: Environment :: Web Environment
Classifier: Intended Audience :: Information Technology
Classifier: Intended Audience :: System Administrators
Classifier: License :: OSI Approved :: MIT License
Classifier: Natural Language :: English
Classifier: Operating System :: OS Independent
Classifier: Programming Language :: Python :: 3
Classifier: Programming Language :: Python :: 3.6
Classifier: Programming Language :: Python :: 3.7
Classifier: Programming Language :: Python :: 3.8
Classifier: Programming Language :: Python :: 3.9
Classifier: Programming Language :: Python :: 3.10
Classifier: Topic :: Communications
Classifier: Topic :: Internet :: WWW/HTTP :: Dynamic Content :: Content Management System
Classifier: Topic :: Internet :: WWW/HTTP :: Site Management
Classifier: Topic :: Office/Business
Classifier: Topic :: Software Development :: Libraries :: Python Modules
Requires-Python: >=3.6
License-File: LICENSE
Requires-Dist: urllib3 (>=1.26.7)
Requires-Dist: requests (>=2.26.0)
Requires-Dist: setuptools (~=52.0.0)
Provides-Extra: sphinx
Requires-Dist: Sphinx (>=3.4.0) ; extra == 'sphinx'
Requires-Dist: sphinxcontrib-applehelp (>=1.0.2) ; extra == 'sphinx'
Requires-Dist: sphinxcontrib-devhelp (>=1.0.2) ; extra == 'sphinx'
Requires-Dist: sphinxcontrib-htmlhelp (>=1.0.3) ; extra == 'sphinx'
Requires-Dist: sphinxcontrib-jsmath (>=1.0.1) ; extra == 'sphinx'
Requires-Dist: sphinxcontrib-qthelp (>=1.0.3) ; extra == 'sphinx'
Requires-Dist: sphinxcontrib-serializinghtml (>=1.1.4) ; extra == 'sphinx'
